.python-version
pykrait/__init__.py
pykrait/__main__.py
pykrait/gui/app.py
pykrait/gui/async_workers.py
pykrait/gui/custom_widgets.py
pykrait/gui/fileselection.py
pykrait/gui/mainwindow.py
pykrait/gui/resources/logo.png
pykrait/io/__init__.py
pykrait/io/files.py
pykrait/io/images.py
pykrait/pipeline/__init__.py
pykrait/pipeline/pipeline.py
pykrait/preprocessing/__init__.py
pykrait/preprocessing/segmentation.py
pykrait/preprocessing/timeseries_extraction.py
pykrait/trace_analysis/__init__.py
pykrait/trace_analysis/filtering.py
pykrait/trace_analysis/oscillations.py
pykrait/trace_analysis/peak_analysis.py
pykrait/trace_analysis/synchronicity.py
pykrait/visualization/image_overlays.py
pykrait-0.3.2.dist-info/METADATA
pykrait-0.3.2.dist-info/WHEEL
pykrait-0.3.2.dist-info/licenses/LICENSE
pykrait-0.3.2.dist-info/RECORD
