Metadata-Version: 2.4
Name: pykrait
Version: 0.3.2
Summary: Python Calcium Recording Analysis and Inference Toolbox
Author-email: phaleanopsis <22663502+phaleanopsis@users.noreply.github.com>
License: MIT
License-File: LICENSE
Requires-Python: >=3.11
Requires-Dist: aicspylibczi>=3.3.1
Requires-Dist: bioio-czi>=2.4.0
Requires-Dist: bioio-imageio
Requires-Dist: bioio-ome-tiff>=1.1.0
Requires-Dist: bioio-tifffile>=1.3.0
Requires-Dist: bioio>=3.0.0
Requires-Dist: cellpose>=4.0.5
Requires-Dist: dask>=2025.5.1
Requires-Dist: fsspec>=2022.8.0
Requires-Dist: imagecodecs>=2025.3.30
Requires-Dist: lxml>=5.4.0
Requires-Dist: matplotlib>=3.10.3
Requires-Dist: numcodecs<0.16
Requires-Dist: numpy>2
Requires-Dist: ome-types>=0.5.3
Requires-Dist: ome-zarr>=0.10.2
Requires-Dist: pandas>=2.3.1
Requires-Dist: pip>=25.1.1
Requires-Dist: pydantic<2
Requires-Dist: pyyaml>=6.0.2
Requires-Dist: resource-backed-dask-array>=0.1.0
Requires-Dist: scikit-image>=0.25.2
Requires-Dist: scikit-learn>=1.7.2
Requires-Dist: scipy>=1.15.3
Requires-Dist: xarray>2025
Requires-Dist: zstandard>=0.23.0
Provides-Extra: dev
Requires-Dist: build>=1.2.2.post1; extra == 'dev'
Requires-Dist: hatch>=1.14.1; extra == 'dev'
Requires-Dist: ipywidgets>=8.1.7; extra == 'dev'
Requires-Dist: pydata-sphinx-theme>=0.16.1; extra == 'dev'
Requires-Dist: pytest-cov; extra == 'dev'
Requires-Dist: pytest>=8.4.1; extra == 'dev'
Requires-Dist: ruff>=0.11.13; extra == 'dev'
Requires-Dist: sphinx-autoapi>=3.6.0; extra == 'dev'
Requires-Dist: sphinx-favicon>=1.0.1; extra == 'dev'
Requires-Dist: sphinx>=8.1.3; extra == 'dev'
Requires-Dist: tomli>=2.2.1; extra == 'dev'
Requires-Dist: twine>=6.1.0; extra == 'dev'
Provides-Extra: gui
Requires-Dist: pyside6>=6.9.1; extra == 'gui'
